{"exp": 152, "rung": "M3e", "layout_seed": 7, "layout_idx": 1, "seed": 0, "plateau": 1.2624784794609494, "final_surprise": 1.3311606997572827, "drop": -0.06868222029633331, "p1_ceiling_events": 809, "phase2_final_ceiling_events": 258, "final_comps_per_color": [1, 1, 1, 1], "jumps_kept": 0, "jumps_reverted": 15, "p1_final500_loc_median": 0.04916157445313707, "p2_final500_loc_median": 0.04115820348113214, "accepted_frac": 0.0, "mean_accepted_delta": null, "total_attempted": 15, "total_accepted": 0, "twin_final500_map_frac": 1.0}
{"exp": 152, "rung": "M3e", "layout_seed": 7, "layout_idx": 1, "seed": 1, "plateau": 1.2340063083703772, "final_surprise": 1.257041114236994, "drop": -0.02303480586661677, "p1_ceiling_events": 1003, "phase2_final_ceiling_events": 354, "final_comps_per_color": [1, 1, 1, 1], "jumps_kept": 0, "jumps_reverted": 15, "p1_final500_loc_median": 0.05547460232417671, "p2_final500_loc_median": 0.047924656156555, "accepted_frac": 0.0, "mean_accepted_delta": null, "total_attempted": 15, "total_accepted": 0, "twin_final500_map_frac": 1.0}
{"exp": 152, "rung": "M3e", "layout_seed": 7, "layout_idx": 1, "seed": 2, "plateau": 1.2695931645571426, "final_surprise": 1.3186444070387455, "drop": -0.049051242481602975, "p1_ceiling_events": 1068, "phase2_final_ceiling_events": 365, "final_comps_per_color": [1, 1, 1, 1], "jumps_kept": 0, "jumps_reverted": 15, "p1_final500_loc_median": 0.06110605528954546, "p2_final500_loc_median": 0.03652835478129737, "accepted_frac": 0.0, "mean_accepted_delta": null, "total_attempted": 15, "total_accepted": 0, "twin_final500_map_frac": 1.0}
{"exp": 152, "rung": "M3e", "layout_seed": 7, "layout_idx": 1, "seed": 3, "plateau": 1.2854227243631093, "final_surprise": 1.2717604628354888, "drop": 0.013662261527620512, "p1_ceiling_events": 951, "phase2_final_ceiling_events": 313, "final_comps_per_color": [1, 1, 1, 1], "jumps_kept": 0, "jumps_reverted": 15, "p1_final500_loc_median": 0.05386205385263809, "p2_final500_loc_median": 0.042046854442057746, "accepted_frac": 0.0, "mean_accepted_delta": null, "total_attempted": 15, "total_accepted": 0, "twin_final500_map_frac": 1.0}
{"exp": 152, "rung": "M3e", "layout_seed": 7, "layout_idx": 1, "seed": 4, "plateau": 1.3267363112074493, "final_surprise": 1.3814578641666435, "drop": -0.05472155295919423, "p1_ceiling_events": 701, "phase2_final_ceiling_events": 142, "final_comps_per_color": [1, 1, 1, 1], "jumps_kept": 0, "jumps_reverted": 15, "p1_final500_loc_median": 0.0539160622539793, "p2_final500_loc_median": 0.0403826680557515, "accepted_frac": 0.0, "mean_accepted_delta": null, "total_attempted": 15, "total_accepted": 0, "twin_final500_map_frac": 1.0}
{"exp": 152, "rung": "M3e", "layout_seed": 7, "layout_idx": 1, "seed": 5, "plateau": 1.2072927699155367, "final_surprise": 1.185440788781416, "drop": 0.02185198113412068, "p1_ceiling_events": 747, "phase2_final_ceiling_events": 416, "final_comps_per_color": [1, 1, 1, 1], "jumps_kept": 0, "jumps_reverted": 15, "p1_final500_loc_median": 0.04391213908742152, "p2_final500_loc_median": 0.04360028072260058, "accepted_frac": 0.0, "mean_accepted_delta": null, "total_attempted": 15, "total_accepted": 0, "twin_final500_map_frac": 1.0}
{"exp": 152, "rung": "M3e", "layout_seed": 7, "layout_idx": 1, "seed": 6, "plateau": 1.2196349681369296, "final_surprise": 1.2825876163446006, "drop": -0.06295264820767099, "p1_ceiling_events": 914, "phase2_final_ceiling_events": 289, "final_comps_per_color": [1, 1, 1, 1], "jumps_kept": 0, "jumps_reverted": 15, "p1_final500_loc_median": 0.058986148127173496, "p2_final500_loc_median": 0.046091140946717526, "accepted_frac": 0.0, "mean_accepted_delta": null, "total_attempted": 15, "total_accepted": 0, "twin_final500_map_frac": 1.0}
{"exp": 152, "rung": "M3e", "layout_seed": 7, "layout_idx": 1, "seed": 7, "plateau": 1.2663220450394133, "final_surprise": 1.2350733014196065, "drop": 0.031248743619806785, "p1_ceiling_events": 630, "phase2_final_ceiling_events": 276, "final_comps_per_color": [1, 1, 1, 1], "jumps_kept": 0, "jumps_reverted": 15, "p1_final500_loc_median": 0.051051603078669565, "p2_final500_loc_median": 0.043455982044279515, "accepted_frac": 0.0, "mean_accepted_delta": null, "total_attempted": 15, "total_accepted": 0, "twin_final500_map_frac": 1.0}
{"exp": 152, "rung": "M3e", "layout_seed": 11, "layout_idx": 2, "seed": 0, "plateau": 1.152187246733797, "final_surprise": 1.200683505605063, "drop": -0.048496258871266074, "p1_ceiling_events": 267, "phase2_final_ceiling_events": 165, "final_comps_per_color": [1, 1, 1, 1], "jumps_kept": 0, "jumps_reverted": 15, "p1_final500_loc_median": 0.04927090492608725, "p2_final500_loc_median": 0.040782780397600485, "accepted_frac": 0.0, "mean_accepted_delta": null, "total_attempted": 15, "total_accepted": 0, "twin_final500_map_frac": 1.0}
{"exp": 152, "rung": "M3e", "layout_seed": 11, "layout_idx": 2, "seed": 1, "plateau": 0.9111777347284705, "final_surprise": 1.1378786102482303, "drop": -0.22670087551975981, "p1_ceiling_events": 438, "phase2_final_ceiling_events": 301, "final_comps_per_color": [4, 1, 1, 1], "jumps_kept": 1, "jumps_reverted": 14, "p1_final500_loc_median": 0.05966591743370184, "p2_final500_loc_median": 0.03953877733969345, "accepted_frac": 0.06666666666666667, "mean_accepted_delta": 0.13782709769309842, "total_attempted": 15, "total_accepted": 1, "twin_final500_map_frac": 1.0}
{"exp": 152, "rung": "M3e", "layout_seed": 11, "layout_idx": 2, "seed": 2, "plateau": 1.044343887482705, "final_surprise": 1.1261153090559792, "drop": -0.08177142157327433, "p1_ceiling_events": 201, "phase2_final_ceiling_events": 213, "final_comps_per_color": [1, 1, 1, 1], "jumps_kept": 0, "jumps_reverted": 14, "p1_final500_loc_median": 0.06180313148096635, "p2_final500_loc_median": 0.03942382707094275, "accepted_frac": 0.0, "mean_accepted_delta": null, "total_attempted": 14, "total_accepted": 0, "twin_final500_map_frac": 1.0}
{"exp": 152, "rung": "M3e", "layout_seed": 11, "layout_idx": 2, "seed": 3, "plateau": 1.142759390705387, "final_surprise": 1.2476858385485994, "drop": -0.10492644784321237, "p1_ceiling_events": 284, "phase2_final_ceiling_events": 260, "final_comps_per_color": [1, 1, 1, 1], "jumps_kept": 0, "jumps_reverted": 14, "p1_final500_loc_median": 0.05329334423666912, "p2_final500_loc_median": 0.04084482996966041, "accepted_frac": 0.0, "mean_accepted_delta": null, "total_attempted": 14, "total_accepted": 0, "twin_final500_map_frac": 1.0}
{"exp": 152, "rung": "M3e", "layout_seed": 11, "layout_idx": 2, "seed": 4, "plateau": 1.043829819038132, "final_surprise": 1.143616536803647, "drop": -0.09978671776551495, "p1_ceiling_events": 487, "phase2_final_ceiling_events": 175, "final_comps_per_color": [1, 1, 1, 1], "jumps_kept": 0, "jumps_reverted": 15, "p1_final500_loc_median": 0.05353795917582518, "p2_final500_loc_median": 0.039645288215522406, "accepted_frac": 0.0, "mean_accepted_delta": null, "total_attempted": 15, "total_accepted": 0, "twin_final500_map_frac": 1.0}
{"exp": 152, "rung": "M3e", "layout_seed": 11, "layout_idx": 2, "seed": 5, "plateau": 1.1306461179277727, "final_surprise": 1.1449089786203595, "drop": -0.014262860692586754, "p1_ceiling_events": 288, "phase2_final_ceiling_events": 212, "final_comps_per_color": [1, 1, 1, 1], "jumps_kept": 0, "jumps_reverted": 15, "p1_final500_loc_median": 0.04378736548994577, "p2_final500_loc_median": 0.043309923417292215, "accepted_frac": 0.0, "mean_accepted_delta": null, "total_attempted": 15, "total_accepted": 0, "twin_final500_map_frac": 1.0}
{"exp": 152, "rung": "M3e", "layout_seed": 11, "layout_idx": 2, "seed": 6, "plateau": 0.9248676092994926, "final_surprise": 1.3176421943495216, "drop": -0.39277458505002893, "p1_ceiling_events": 279, "phase2_final_ceiling_events": 165, "final_comps_per_color": [1, 1, 1, 1], "jumps_kept": 0, "jumps_reverted": 14, "p1_final500_loc_median": 0.05761258406043735, "p2_final500_loc_median": 0.043799429835099685, "accepted_frac": 0.0, "mean_accepted_delta": null, "total_attempted": 14, "total_accepted": 0, "twin_final500_map_frac": 1.0}
{"exp": 152, "rung": "M3e", "layout_seed": 11, "layout_idx": 2, "seed": 7, "plateau": 1.0869550068278744, "final_surprise": 1.177601343388173, "drop": -0.09064633656029852, "p1_ceiling_events": 611, "phase2_final_ceiling_events": 215, "final_comps_per_color": [1, 1, 1, 1], "jumps_kept": 0, "jumps_reverted": 13, "p1_final500_loc_median": 0.051774047402646434, "p2_final500_loc_median": 0.042627576447811524, "accepted_frac": 0.0, "mean_accepted_delta": null, "total_attempted": 13, "total_accepted": 0, "twin_final500_map_frac": 1.0}
{"exp": 152, "rung": "M3e", "layout_seed": 13, "layout_idx": 3, "seed": 0, "plateau": 0.6714396588072551, "final_surprise": 0.7713375721072729, "drop": -0.09989791330001785, "p1_ceiling_events": 535, "phase2_final_ceiling_events": 250, "final_comps_per_color": [1, 1, 1, 1], "jumps_kept": 0, "jumps_reverted": 10, "p1_final500_loc_median": 0.04968515779610093, "p2_final500_loc_median": 0.04300824476603125, "accepted_frac": 0.0, "mean_accepted_delta": null, "total_attempted": 10, "total_accepted": 0, "twin_final500_map_frac": 1.0}
{"exp": 152, "rung": "M3e", "layout_seed": 13, "layout_idx": 3, "seed": 1, "plateau": 0.7665512613306236, "final_surprise": 0.7337966940345889, "drop": 0.03275456729603465, "p1_ceiling_events": 598, "phase2_final_ceiling_events": 81, "final_comps_per_color": [1, 4, 1, 1], "jumps_kept": 3, "jumps_reverted": 7, "p1_final500_loc_median": 0.0552072808467757, "p2_final500_loc_median": 0.041401315593915244, "accepted_frac": 0.3, "mean_accepted_delta": 0.22208160693993814, "total_attempted": 10, "total_accepted": 3, "twin_final500_map_frac": 1.0}
{"exp": 152, "rung": "M3e", "layout_seed": 13, "layout_idx": 3, "seed": 2, "plateau": 0.7998881932163898, "final_surprise": 0.7460929982776794, "drop": 0.05379519493871043, "p1_ceiling_events": 243, "phase2_final_ceiling_events": 116, "final_comps_per_color": [1, 1, 1, 1], "jumps_kept": 0, "jumps_reverted": 11, "p1_final500_loc_median": 0.061725930876733365, "p2_final500_loc_median": 0.04195384765222383, "accepted_frac": 0.0, "mean_accepted_delta": null, "total_attempted": 11, "total_accepted": 0, "twin_final500_map_frac": 1.0}
{"exp": 152, "rung": "M3e", "layout_seed": 13, "layout_idx": 3, "seed": 3, "plateau": 0.8613183547677775, "final_surprise": 0.7222114510327843, "drop": 0.13910690373499324, "p1_ceiling_events": 506, "phase2_final_ceiling_events": 242, "final_comps_per_color": [1, 1, 1, 1], "jumps_kept": 0, "jumps_reverted": 10, "p1_final500_loc_median": 0.05326947031129167, "p2_final500_loc_median": 0.04402915460821543, "accepted_frac": 0.0, "mean_accepted_delta": null, "total_attempted": 10, "total_accepted": 0, "twin_final500_map_frac": 1.0}
{"exp": 152, "rung": "M3e", "layout_seed": 13, "layout_idx": 3, "seed": 4, "plateau": 0.7079464483689508, "final_surprise": 0.773413241310102, "drop": -0.06546679294115121, "p1_ceiling_events": 228, "phase2_final_ceiling_events": 210, "final_comps_per_color": [1, 1, 1, 1], "jumps_kept": 0, "jumps_reverted": 10, "p1_final500_loc_median": 0.052516212541636895, "p2_final500_loc_median": 0.03970821825798233, "accepted_frac": 0.0, "mean_accepted_delta": null, "total_attempted": 10, "total_accepted": 0, "twin_final500_map_frac": 1.0}
{"exp": 152, "rung": "M3e", "layout_seed": 13, "layout_idx": 3, "seed": 5, "plateau": 0.7702221100360789, "final_surprise": 0.7239717914654669, "drop": 0.046250318570612015, "p1_ceiling_events": 341, "phase2_final_ceiling_events": 296, "final_comps_per_color": [1, 1, 1, 1], "jumps_kept": 0, "jumps_reverted": 11, "p1_final500_loc_median": 0.043800402355165344, "p2_final500_loc_median": 0.0455912126606747, "accepted_frac": 0.0, "mean_accepted_delta": null, "total_attempted": 11, "total_accepted": 0, "twin_final500_map_frac": 1.0}
{"exp": 152, "rung": "M3e", "layout_seed": 13, "layout_idx": 3, "seed": 6, "plateau": 0.7269951062298564, "final_surprise": 0.835534330393478, "drop": -0.1085392241636216, "p1_ceiling_events": 249, "phase2_final_ceiling_events": 192, "final_comps_per_color": [1, 1, 1, 1], "jumps_kept": 0, "jumps_reverted": 11, "p1_final500_loc_median": 0.060737595823306074, "p2_final500_loc_median": 0.05160073018041187, "accepted_frac": 0.0, "mean_accepted_delta": null, "total_attempted": 11, "total_accepted": 0, "twin_final500_map_frac": 1.0}
{"exp": 152, "rung": "M3e", "layout_seed": 13, "layout_idx": 3, "seed": 7, "plateau": 0.727616680501888, "final_surprise": 0.7302096819784005, "drop": -0.0025930014765125353, "p1_ceiling_events": 495, "phase2_final_ceiling_events": 223, "final_comps_per_color": [1, 1, 1, 1], "jumps_kept": 0, "jumps_reverted": 11, "p1_final500_loc_median": 0.052340633915304496, "p2_final500_loc_median": 0.04664075032378942, "accepted_frac": 0.0, "mean_accepted_delta": null, "total_attempted": 11, "total_accepted": 0, "twin_final500_map_frac": 1.0}
{"exp": 152, "rung": "M3e", "layout_seed": 7, "layout_idx": 1, "seed": -1, "summary": true, "p1_holds": false, "p1_drop_count": 0, "p1_quiet_count": 0, "p1_comps_count": 0, "p2_holds": false, "p2_delta_holds": false, "p2_frac_holds": false, "mean_delta_layout": null, "accepted_frac_layout": 0.0, "p3_holds": true, "p3_count": 8, "twin_holds": true, "twin_count": 8}
{"exp": 152, "rung": "M3e", "layout_seed": 11, "layout_idx": 2, "seed": -1, "summary": true, "p1_holds": false, "p1_drop_count": 0, "p1_quiet_count": 0, "p1_comps_count": 0, "p2_holds": false, "p2_delta_holds": false, "p2_frac_holds": false, "mean_delta_layout": 0.13782709769309842, "accepted_frac_layout": 0.008695652173913044, "p3_holds": true, "p3_count": 8, "twin_holds": true, "twin_count": 8}
{"exp": 152, "rung": "M3e", "layout_seed": 13, "layout_idx": 3, "seed": -1, "summary": true, "p1_holds": false, "p1_drop_count": 0, "p1_quiet_count": 0, "p1_comps_count": 0, "p2_holds": false, "p2_delta_holds": false, "p2_frac_holds": false, "mean_delta_layout": 0.22208160693993814, "accepted_frac_layout": 0.03571428571428571, "p3_holds": true, "p3_count": 8, "twin_holds": true, "twin_count": 8}
{"exp": 152, "rung": "M3e", "seed": -2, "global_summary": true, "p1_global": false, "p2_global": false, "p3_global": true, "halt_migration_p1": true, "halt_regression": false, "verdict": "NEGATIVE"}
